freeiam/_version.py
freeiam/errors.py
freeiam/ldap/__init__.py
freeiam/ldap/_wrapper.py
freeiam/ldap/attr.py
freeiam/ldap/connection.py
freeiam/ldap/constants.py
freeiam/ldap/controls.py
freeiam/ldap/dn.py
freeiam/ldap/filter.py
freeiam/ldap/pool.py
freeiam/ldap/schema.py
freeiam/ldap/sync_connection.py
freeiam-0.7.0.dist-info/METADATA
freeiam-0.7.0.dist-info/WHEEL
freeiam-0.7.0.dist-info/top_level.txt
freeiam-0.7.0.dist-info/RECORD
