Metadata-Version: 2.4
Name: freeiam
Version: 0.7.0
Summary: FreeIAM is a free and flexible Identity and Access Management solution.
Author-email: Florian Best <contact@freeiam.org>
Project-URL: homepage, https://freeiam.org
Project-URL: documentation, https://docs.freeiam.org
Project-URL: repository, https://github.com/Free-IAM/freeiam
Project-URL: changelog, https://github.com/Free-IAM/freeiam/blob/main/CHANGELOG.md
Requires-Python: >=3.11
Requires-Dist: python-ldap
Requires-Dist: lark
Provides-Extra: dev
Requires-Dist: build; extra == "dev"
Requires-Dist: cryptography; extra == "dev"
Requires-Dist: pytest; extra == "dev"
Requires-Dist: pytest-asyncio; extra == "dev"
Requires-Dist: pytest-benchmark; extra == "dev"
Requires-Dist: pytest-cov; extra == "dev"
Requires-Dist: pytest-timeout; extra == "dev"
Requires-Dist: tox; extra == "dev"
Requires-Dist: testcontainers[docker]; extra == "dev"
Requires-Dist: python-semantic-release; extra == "dev"
Provides-Extra: test
Requires-Dist: cryptography; extra == "test"
Requires-Dist: pytest; extra == "test"
Requires-Dist: pytest-asyncio; extra == "test"
Requires-Dist: pytest-benchmark; extra == "test"
Requires-Dist: pytest-cov; extra == "test"
Requires-Dist: pytest-timeout; extra == "test"
Requires-Dist: testcontainers[docker]; extra == "test"
Provides-Extra: docs
Requires-Dist: lark; extra == "docs"
Requires-Dist: sphinx; extra == "docs"
Requires-Dist: furo; extra == "docs"
Provides-Extra: benchmark
Requires-Dist: ldap3; extra == "benchmark"
Requires-Dist: bonsai; extra == "benchmark"
